app/__init__.py
app/main.py
app/src/__init__.py
app/src/my_import.py
app/tests/__init__.py
app/tests/test_main.py
autodownload_from_clipboard-0.1.1.dist-info/METADATA
autodownload_from_clipboard-0.1.1.dist-info/WHEEL
autodownload_from_clipboard-0.1.1.dist-info/entry_points.txt
autodownload_from_clipboard-0.1.1.dist-info/licenses/LICENSE
autodownload_from_clipboard-0.1.1.dist-info/RECORD
