Metadata-Version: 2.4
Name: autodownload-from-clipboard
Version: 0.1.1
Summary: An executable tool to automatically download videos and images from urls in the clipboard
Project-URL: Source, https://github.com/DSestu/autodownload-from-clipboard
Project-URL: Issues, https://github.com/DSestu/autodownload-from-clipboard/issues
Project-URL: Changelog, https://github.com/DSestu/autodownload-from-clipboard/releases
Project-URL: License, https://github.com/DSestu/autodownload-from-clipboard/blob/main/LICENSE
Author-email: DSestu <david.sestu@gmail.com>
License-File: LICENSE
Requires-Python: <3.12,>=3.11
Requires-Dist: pre-commit>=3.8.0
Requires-Dist: pytest>=8.3.2
Requires-Dist: ruff>=0.6.3
